Metadata-Version: 1.1
Name: kamrakamri-OOP
Version: 62.51
Summary: A text-based adventure game using OOP
Home-page: UNKNOWN
Author: Raz Raza
Author-email: abcrazzak20@gmail.com
License: UNKNOWN
Platform: UNKNOWN
Classifier: Development Status :: 1 - Planning
Classifier: Intended Audience :: Education
Classifier: Programming Language :: Python :: 3
Classifier: Operating System :: OS Independent
